odoo/addons/base_fontawesome/README.rst
odoo/addons/base_fontawesome/__init__.py
odoo/addons/base_fontawesome/__manifest__.py
odoo/addons/base_fontawesome/i18n/base_fontawesome.pot
odoo/addons/base_fontawesome/i18n/es_AR.po
odoo/addons/base_fontawesome/i18n/es_ES.po
odoo/addons/base_fontawesome/i18n/it.po
odoo/addons/base_fontawesome/i18n/zh_CN.po
odoo/addons/base_fontawesome/readme/CONTRIBUTORS.md
odoo/addons/base_fontawesome/readme/DESCRIPTION.md
odoo/addons/base_fontawesome/readme/USAGE.md
odoo/addons/base_fontawesome/static/description/icon.png
odoo/addons/base_fontawesome/static/description/index.html
odoo/addons/base_fontawesome/static/lib/fontawesome-6.6.0/css/all.css
odoo/addons/base_fontawesome/static/lib/fontawesome-6.6.0/css/v4-shims.css
odoo/addons/base_fontawesome/static/lib/fontawesome-6.6.0/webfonts/fa-brands-400.ttf
odoo/addons/base_fontawesome/static/lib/fontawesome-6.6.0/webfonts/fa-brands-400.woff2
odoo/addons/base_fontawesome/static/lib/fontawesome-6.6.0/webfonts/fa-regular-400.ttf
odoo/addons/base_fontawesome/static/lib/fontawesome-6.6.0/webfonts/fa-regular-400.woff2
odoo/addons/base_fontawesome/static/lib/fontawesome-6.6.0/webfonts/fa-solid-900.ttf
odoo/addons/base_fontawesome/static/lib/fontawesome-6.6.0/webfonts/fa-solid-900.woff2
odoo/addons/base_fontawesome/static/lib/fontawesome-6.6.0/webfonts/fa-v4compatibility.ttf
odoo/addons/base_fontawesome/static/lib/fontawesome-6.6.0/webfonts/fa-v4compatibility.woff2
odoo/addons/base_fontawesome/static/src/css/fontawesome.css
odoo_addon_base_fontawesome-18.0.1.0.0.2.dist-info/METADATA
odoo_addon_base_fontawesome-18.0.1.0.0.2.dist-info/WHEEL
odoo_addon_base_fontawesome-18.0.1.0.0.2.dist-info/top_level.txt
odoo_addon_base_fontawesome-18.0.1.0.0.2.dist-info/RECORD
