Metadata-Version: 2.1
Name: odoo-addon-base_fontawesome
Version: 18.0.1.0.0.2
Requires-Python: >=3.10
Requires-Dist: odoo==18.0.*
Summary: Up to date Fontawesome resources.
Home-page: https://github.com/OCA/server-tools
License: LGPL-3
Author: Camptocamp,Creu Blanca,Odoo Community Association (OCA)
Author-email: support@odoo-community.org
Classifier: Programming Language :: Python
Classifier: Framework :: Odoo
Classifier: Framework :: Odoo :: 18.0
Classifier: License :: OSI Approved :: GNU Lesser General Public License v3 (LGPLv3)
